LICENSE
README.md
pyproject.toml
setup.py
ksuid/__init__.py
ksuid/ksuid.py
ksuid/py.typed
svix_ksuid.egg-info/PKG-INFO
svix_ksuid.egg-info/SOURCES.txt
svix_ksuid.egg-info/dependency_links.txt
svix_ksuid.egg-info/not-zip-safe
svix_ksuid.egg-info/requires.txt
svix_ksuid.egg-info/top_level.txt
tests/test_ksuid.py